gcloud_functions_utils/__init__.py
gcloud_functions_utils/clients/__init__.py
gcloud_functions_utils/clients/pubsub/__init__.py
gcloud_functions_utils/clients/pubsub/pubsub_client.py
gcloud_functions_utils/factories/__init__.py
gcloud_functions_utils/factories/trigger/__init__.py
gcloud_functions_utils/factories/trigger/pubsub/__init__.py
gcloud_functions_utils/factories/trigger/pubsub/context_event_type.py
gcloud_functions_utils/factories/trigger/pubsub/context_factory.py
gcloud_functions_utils/factories/trigger/pubsub/context_mock.py
gcloud_functions_utils/factories/trigger/pubsub/event_factory.py
gcloud_functions_utils/parsers/__init__.py
gcloud_functions_utils/parsers/trigger/__init__.py
gcloud_functions_utils/parsers/trigger/pubsub/__init__.py
gcloud_functions_utils/parsers/trigger/pubsub/context_parser.py
gcloud_functions_utils/parsers/trigger/pubsub/event_parser.py
gcloud_functions_utils/test_tools/__init__.py
gcloud_functions_utils/test_tools/local_client/__init__.py
gcloud_functions_utils/test_tools/local_client/pubsub/__init__.py
gcloud_functions_utils/test_tools/local_client/pubsub/local_pubsub_client.py
gcloud_functions_utils/utils/__init__.py
gcloud_functions_utils/utils/secret_manager.py
gcloud_functions_utils-0.13.0.dist-info/METADATA
gcloud_functions_utils-0.13.0.dist-info/WHEEL
gcloud_functions_utils-0.13.0.dist-info/top_level.txt
gcloud_functions_utils-0.13.0.dist-info/RECORD
