Metadata-Version: 2.1
Name: gcloud-functions-utils
Version: 0.13.0
Summary: UNKNOWN
Home-page: https://github.com/vonNiklasson/gcloud-functions-utils
Author: Johan Niklasson
Author-email: johan@niklasson.me
License: UNKNOWN
Platform: UNKNOWN
Classifier: Intended Audience :: Developers
Classifier: Programming Language :: Python
Classifier: Programming Language :: Python :: 3
Classifier: Operating System :: OS Independent
Requires-Python: >=3.5
Requires-Dist: google-cloud-pubsub (<3,>=2.2.0)
Requires-Dist: google-cloud-secret-manager (<3,>=2.1.0)
Provides-Extra: test-tools
Requires-Dist: functions-framework (<3,>=2.1.0) ; extra == 'test-tools'
Requires-Dist: requests (<3,>=2.20.0) ; extra == 'test-tools'
